timeserious/__init__.py
timeserious/transform.py
timeserious-0.0.1.dist-info/LICENSE
timeserious-0.0.1.dist-info/METADATA
timeserious-0.0.1.dist-info/WHEEL
timeserious-0.0.1.dist-info/top_level.txt
timeserious-0.0.1.dist-info/RECORD
