Metadata-Version: 2.1
Name: timeserious
Version: 0.0.1
Summary: A package for timeseries
Author: Fabian Kropfhamer
Project-URL: Homepage, https://github.com/fkropfhamer/timeserious
Project-URL: Bug Tracker, https://github.com/fkropfhamer/timeserious/issues
Classifier: Programming Language :: Python :: 3
Classifier: License :: OSI Approved :: MIT License
Classifier: Operating System :: OS Independent
Requires-Python: >=3.7
License-File: LICENSE
